{  
   "Items":[  
      {  
         "id":"2519778463462065578",
         "timeValue":"2015-02-20T17:47:33.7934421Z",
         "value":[  
            {  
               "resourceId":9958,
               "value":1894.73318646107
            }
         ]
      },
      {  
         "id":"2519778464054291212",
         "timeValue":"2015-02-20T17:46:34.5708787Z",
         "value":[  
            {  
               "resourceId":9958,
               "value":1894.73318646107
            }
         ]
      },
      {  
         "id":"2519778465856393198",
         "timeValue":"2015-02-20T17:43:34.3606801Z",
         "value":[  
            {  
               "resourceId":9958,
               "value":1894.73318646107
            }
         ]
      },
      {  
         "id":"2519778466449869577",
         "timeValue":"2015-02-20T17:42:35.0130422Z",
         "value":[  
            {  
               "resourceId":9958,
               "value":1894.73318646107
            }
         ]
      },
      {  
         "id":"2519778467064343378",
         "timeValue":"2015-02-20T17:41:33.5656621Z",
         "value":[  
            {  
               "resourceId":9958,
               "value":1894.73318646107
            }
         ]
      }
   ],
   "Count":5
}